MANIFEST.in
README.rst
setup.py
xbob/__init__.py
xbob.extension.egg-info/PKG-INFO
xbob.extension.egg-info/SOURCES.txt
xbob.extension.egg-info/dependency_links.txt
xbob.extension.egg-info/namespace_packages.txt
xbob.extension.egg-info/requires.txt
xbob.extension.egg-info/top_level.txt
xbob.extension.egg-info/zip-safe
xbob/extension/__init__.py