Metadata-Version: 1.1
Name: xbob.extension
Version: 0.2.0
Summary: Helps projects building Python/C++ extensions for Bob
Home-page: http://pypi.python.org/pypi/xbob.extension
Author: Andre Anjos
Author-email: andre.anjos@idiap.ch
License: GPLv3
Platform: UNKNOWN
Classifier: Development Status :: 3 - Alpha
Classifier: Intended Audience :: Developers
Classifier: License :: OSI Approved :: GNU General Public License v3 (GPLv3)
Classifier: Natural Language :: English
Classifier: Programming Language :: Python
Classifier: Programming Language :: Python :: 3
Classifier: Topic :: Software Development :: Libraries :: Python Modules
